[   
    {
        "name": "婚前试爱(2010)",
        "thumb": "http://ww1.sinaimg.cn/mw690/005BjCpAgw1f0zut9lmesj30bw0goq65.jpg",
        "url": "http://www.q2002.com/show/2955.html"
    },
    {
        "name": "一路向西 (2012)",
        "thumb": "http://wx3.sinaimg.cn/mw690/006xTuHMgy1fdhqzxnp7jj30be0gojuv.jpg",
        "url": "http://www.q2002.com/show/40553.html"
    },
    {
        "name": "鸭王 (2015)",
        "thumb": "http://ww1.sinaimg.cn/mw690/005BjCpAgw1exh9ot4ptpj30bu0go42z.jpg",
        "url": "http://www.q2002.com/show/82.html"
    },
    {
        "name": "鸭王2 (2016)",
        "thumb": "http://ww2.sinaimg.cn/mw690/005BjCpAgw1f1zqs44meij30bu0gowik.jpg",
        "url": "http://www.q2002.com/show/3958.html"
    },
    {
        "name": "西虹市首富",
        "thumb": "http://wx4.sinaimg.cn/mw690/80df6fe6gy1ftq9nowqlwj20iv0qedjw.jpg",
        "url": "http://www.q2002.com/show/44973.html"
    },
    {
        "name": "狄仁杰之四大天王",
        "thumb": "http://wx4.sinaimg.cn/mw690/80df6fe6gy1ftsgbdojybj20u0160129.jpg",
        "url": "http://www.q2002.com/show/45031.html"
    },
    {
        "name": "我不是药神",
        "thumb": "http://wx4.sinaimg.cn/mw690/80df6fe6gy1fsw1achwe0j20u0160q92.jpg",
        "url": "http://www.q2002.com/show/44185.html"
    },
    {
        "name": "战狼2",
        "thumb": "http://wx3.sinaimg.cn/mw690/005BjCpAgy1fc277xlwxdj30bw0goade.jpg",
        "url": "http://www.q2002.com/show/21644.html"
    },
    {
        "name": "战狼",
        "thumb": "http://ww4.sinaimg.cn/mw690/005BjCpAgw1exew57xew8j30bx0gon13.jpg",
        "url": "http://www.q2002.com/show/55.html"
    },
    {
        "name": "战狼传说 (1997)",
        "thumb": "http://ww4.sinaimg.cn/mw690/005BjCpAgw1f250d7sy5zj30bl0goq5f.jpg",
        "url": "http://www.q2002.com/show/4121.html"
    },
    {
        "name": "杀破狼",
        "thumb": "http://ww2.sinaimg.cn/mw690/005BjCpAgw1ezcfdxa5evj30b40go778.jpg",
        "url": "http://www.q2002.com/show/1448.html"
    },
    {
        "name": "杀破狼·贪狼(2017)",
        "thumb": "http://wx1.sinaimg.cn/mw690/80df6fe6ly1fiq7dvttm1j20bw0gotcu.jpg",
        "url": "http://www.q2002.com/show/31743.html"
    },
    {
        "name": "杀破狼2",
        "thumb": "http://ww3.sinaimg.cn/mw690/005BjCpAgw1exegoxb9dhj30bp0godji.jpg",
        "url": "http://www.q2002.com/show/46.html"
    },
    {
        "name": "导火线",
        "thumb": "http://ww2.sinaimg.cn/mw690/005BjCpAjw1f5pebdvycxj30bo0gotb0.jpg",
        "url": "http://www.q2002.com/show/10541.html"
    },
    {
        "name": "夺帅(2008)",
        "thumb": "http://ww1.sinaimg.cn/mw690/005BjCpAgw1f3085p7gjoj30bn0goju0.jpg",
        "url": "http://www.q2002.com/show/5135.html"
    },
    {
        "name": "师父 (2015)",
        "thumb": "http://ww1.sinaimg.cn/mw690/005BjCpAgw1eyr5zz8l5hj30bw0gotc5.jpg",
        "url": "http://www.q2002.com/show/1077.html"
    },
    {
        "name": "男儿本色 (2007)",
        "thumb": "http://ww2.sinaimg.cn/mw690/005BjCpAgw1f4dt6v8y9aj30bs0godiv.jpg",
        "url": "http://www.q2002.com/show/7372.html"
    },
    {
        "name": "生死拳 黑拳 (2006)",
        "thumb": "http://ww2.sinaimg.cn/mw690/005BjCpAgw1f26opnghvnj30b40fp780.jpg",
        "url": "http://www.q2002.com/show/4213.html"
    },
    {
        "name": "绣春刀 (2014)",
        "thumb": "http://ww1.sinaimg.cn/mw690/005BjCpAgw1f41bfhahzej30b10goads.jpg",
        "url": "http://www.q2002.com/show/6512.html"
    },
    {
        "name": "绣春刀II：修罗战场 (2017)",
        "thumb": "http://wx4.sinaimg.cn/mw690/80df6fe6ly1fi2s03d6hej20br0gowj4.jpg",
        "url": "http://www.q2002.com/show/31161.html"
    },
    {
        "name": "西风烈 (2010)",
        "thumb": "http://ww2.sinaimg.cn/mw690/005BjCpAgw1faiu7oeinwj309z0goada.jpg",
        "url": "http://www.q2002.com/show/19249.html"
    },
    {
        "name": "双子神偷",
        "thumb": "http://ww4.sinaimg.cn/mw690/005BjCpAgw1fbtn1ws0rnj30c10go0vo.jpg",
        "url": "http://www.q2002.com/show/21266.html"
    },
    {
        "name": "乘风破浪 (2017)",
        "thumb": "http://wx1.sinaimg.cn/mw690/005BjCpAgy1fc6w9xmyn4j30cj0gojuw.jpg",
        "url": "http://www.q2002.com/show/21850.html"
    },
    {
        "name": "从你的全世界路过 (2016)",
        "thumb": "http://ww4.sinaimg.cn/mw690/005BjCpAjw1f86fh8o5xxj30bx0go43e.jpg",
        "url": "http://www.q2002.com/show/15300.html"
    },
    {
        "name": "分手大师 (2014)",
        "thumb": "http://wx1.sinaimg.cn/mw690/005BjCpAgy1fe87y9gusxj30bw0gogo4.jpg",
        "url": "http://www.q2002.com/show/25270.html"
    },
    {
        "name": "恶棍天使 (2015)",
        "thumb": "http://ww2.sinaimg.cn/mw690/005BjCpAgw1ez5jgdvxy5j30bw0godk0.jpg",
        "url": "http://www.q2002.com/show/1310.html"
    },
    {
        "name": "烈日灼心 (2015)",
        "thumb": "http://ww2.sinaimg.cn/mw690/005BjCpAgw1f3pa526hk2j30bw0gojuf.jpg",
        "url": "http://www.q2002.com/show/27.html"
    },
    {
        "name": "中国合伙人 (2013)",
        "thumb": "http://ww4.sinaimg.cn/mw690/005BjCpAgw1eyslg5t84xj30ba0gotdw.jpg",
        "url": "http://www.q2002.com/show/1121.html"
    },
    {
        "name": "缝纫机乐队 (2017)",
        "thumb": "http://wx4.sinaimg.cn/mw690/80df6fe6gy1fkq4i765adj20u0160wnj.jpg",
        "url": "http://www.q2002.com/show/34551.html"
    },
    {
        "name": "全城戒备 (2010)",
        "thumb": "http://ww4.sinaimg.cn/mw690/005BjCpAgw1f4h0ueqmwrj30bw0gowhl.jpg",
        "url": "http://www.q2002.com/show/7570.html"
    },
    {
        "name": "羞羞的铁拳 (2017)",
        "thumb": "http://wx1.sinaimg.cn/mw690/80df6fe6ly1fk4xm34o4kj20u015zai7.jpg",
        "url": "http://www.q2002.com/show/33562.html"
    },
    {
        "name": "心花路放 (2014)",
        "thumb": "http://ww3.sinaimg.cn/mw690/005BjCpAgw1f0uzg92gwoj30bw0gotbm.jpg",
        "url": "http://www.q2002.com/show/2795.html"
    },
    {
        "name": "夏洛特烦恼 (2015)",
        "thumb": "http://ww4.sinaimg.cn/mw690/005BjCpAgw1exbm36s0h3j30bw0goadt.jpg",
        "url": "http://www.q2002.com/show/1.html"
    },
    {
        "name": "非凡任务 (2017)",
        "thumb": "http://wx2.sinaimg.cn/mw690/005BjCpAgy1fe9aohqu5cj30bw0go42y.jpg",
        "url": "http://www.q2002.com/show/25333.html"
    },
    {
        "name": "极限特工3：终极回归",
        "thumb": "http://wx4.sinaimg.cn/mw690/005BjCpAgy1fcczu3d45nj30b90gogog.jpg",
        "url": "http://www.q2002.com/show/22144.html"
    },
    {
        "name": "致我们终将逝去的青春 (2013)",
        "thumb": "http://ww2.sinaimg.cn/mw690/005BjCpAgw1f0gv7wdo9xj30by0go0wi.jpg",
        "url": "http://www.q2002.com/show/2375.html"
    },
    {
        "name": "使徒行者",
        "thumb": "http://ww1.sinaimg.cn/mw690/005BjCpAjw1f6ptncaltvj30bu0goq6o.jpg",
        "url": "http://www.q2002.com/show/12083.html"
    },
    {
        "name": "中华赌侠 (2000)",
        "thumb": "http://wx3.sinaimg.cn/mw690/80df6fe6gy1fpt1dwstlej20fv0m8ahi.jpg",
        "url": "http://www.q2002.com/show/41198.html"
    },
    {
        "name": "线人 (2010)",
        "thumb": "http://ww4.sinaimg.cn/mw690/005BjCpAjw1f8r6kdq23qj30bu0go0w7.jpg",
        "url": "http://www.q2002.com/show/41198.html"
    },
    {
        "name": "赤道 (2015)",
        "thumb": "http://ww1.sinaimg.cn/mw690/005BjCpAgw1f23gb33l1cj30bx0go422.jpg",
        "url": "http://www.q2002.com/show/4060.html"
    },
    {
        "name": "澳门风云3",
        "thumb": "http://ww3.sinaimg.cn/mw690/005BjCpAgw1f0fw1gufm3j30bw0gogq2.jpg",
        "url": "http://www.q2002.com/show/2333.html"
    },
    {
        "name": "新龙门客栈(1992)",
        "thumb": "http://ww4.sinaimg.cn/mw690/005BjCpAgw1f3tnbcnlx5j30b30go77t.jpg",
        "url": "http://www.q2002.com/show/6031.html"
    },
    {
        "name": "龙门飞甲 (2011)",
        "thumb": "http://ww3.sinaimg.cn/mw690/005BjCpAgw1f9n941vx8mj30bo0gon18.jpg",
        "url": "http://www.q2002.com/show/18131.html"
    },
    {
        "name": "智取威虎山 (2014)",
        "thumb": "http://ww2.sinaimg.cn/mw690/005BjCpAgw1f3trusqk4sj30bw0gogq3.jpg",
        "url": "http://www.q2002.com/show/6042.html"
    },
    {
        "name": "笑傲江湖2：东方不败",
        "thumb": "http://ww2.sinaimg.cn/mw690/005BjCpAgw1f4qmrjm8z3j30b70gotd8.jpg",
        "url": "http://www.q2002.com/show/8332.html"
    },
    {
        "name": "倩女幽魂3",
        "thumb": "http://ww4.sinaimg.cn/mw690/005BjCpAgw1eyeyf9jwyyj30b40gomzm.jpg",
        "url": "http://www.q2002.com/show/824.html"
    }
]